{
  "system": {
    "status": "running",
    "pid": 22208,
    "start_time": "2025-12-28T15:00:16.038787",
    "last_heartbeat": "2025-12-28T21:10:42.302024",
    "heartbeat_ago": 0
  },
  "config": {
    "mode": "neutral",
    "strategy": "st-exchange",
    "interval": 5
  },
  "schedule": {
    "last_run": null,
    "next_run": "2025-12-28T21:10:52.303724",
    "time_remaining": 10,
    "message": "Next Monitoring Cycle"
  },
  "logic": {
    "current_action": "Exchange Waiting",
    "market_status": "Unknown",
    "description": "Target: 월 23:33 (Wait: 1일 2:22:27)"
  },
  "last_updated": "2025-12-28T21:10:42.303724",
  "market": {
    "current_price": 55.31,
    "details": {
      "cash": 1063.443475,
      "holdings_qty": 38,
      "avg_price": 55.3121
    }
  }
}